mendeley_mcp/__init__.py
mendeley_mcp/auth.py
mendeley_mcp/client.py
mendeley_mcp/server.py
mendeley_mcp-0.1.3.dist-info/METADATA
mendeley_mcp-0.1.3.dist-info/WHEEL
mendeley_mcp-0.1.3.dist-info/entry_points.txt
mendeley_mcp-0.1.3.dist-info/licenses/LICENSE
mendeley_mcp-0.1.3.dist-info/RECORD
