Metadata-Version: 2.4
Name: mendeley-mcp
Version: 0.1.3
Summary: MCP server for Mendeley reference manager - search, retrieve, and manage your academic library
Project-URL: Homepage, https://github.com/pallaprolus/mendeley-mcp
Project-URL: Repository, https://github.com/pallaprolus/mendeley-mcp
Project-URL: Issues, https://github.com/pallaprolus/mendeley-mcp/issues
Author: Sudhakar Pallaprolu
License: MIT
License-File: LICENSE
Keywords: academic,citations,mcp,mendeley,reference-manager,research
Classifier: Development Status :: 4 - Beta
Classifier: Intended Audience :: Science/Research
Classifier: License :: OSI Approved :: MIT License
Classifier: Programming Language :: Python :: 3
Classifier: Programming Language :: Python :: 3.10
Classifier: Programming Language :: Python :: 3.11
Classifier: Programming Language :: Python :: 3.12
Classifier: Topic :: Scientific/Engineering
Requires-Python: >=3.10
Requires-Dist: click>=8.0.0
Requires-Dist: httpx>=0.27.0
Requires-Dist: keyring>=25.0.0
Requires-Dist: mcp>=1.2.0
Requires-Dist: pydantic>=2.0.0
Provides-Extra: dev
Requires-Dist: mypy>=1.10.0; extra == 'dev'
Requires-Dist: pytest-asyncio>=0.23.0; extra == 'dev'
Requires-Dist: pytest>=8.0.0; extra == 'dev'
Requires-Dist: ruff>=0.4.0; extra == 'dev'
